mera-1.6.0.post1.data/purelib/mera/__init__.py
mera-1.6.0.post1.data/purelib/mera/deploy.py
mera-1.6.0.post1.data/purelib/mera/deploy_project.py
mera-1.6.0.post1.data/purelib/mera/mera_deployment.py
mera-1.6.0.post1.data/purelib/mera/mera_model.py
mera-1.6.0.post1.data/purelib/mera/mera_platform.py
mera-1.6.0.post1.data/purelib/mera/mera_quantizer.py
mera-1.6.0.post1.data/purelib/mera/quantization_quality.py
mera-1.6.0.post1.data/purelib/mera/version.py
mera-1.6.0.post1.data/purelib/mera/app/__init__.py
mera-1.6.0.post1.data/purelib/mera/app/mera.py
mera-1.6.0.post1.data/purelib/mera/bin_utils/__init__.py
mera-1.6.0.post1.data/purelib/mera/bin_utils/ec_dma_daemon_proc
mera-1.6.0.post1.data/purelib/mera/bin_utils/ifc_uio_5.15.0-56-generic.ko
mera-1.6.0.post1.data/purelib/mera/bin_utils/intel_get_board_id
mera-1.6.0.post1.data/purelib/mera/bin_utils/sakura_ddr_init
mera-1.6.0.post1.data/purelib/mera/metrics/__init__.py
mera-1.6.0.post1.data/purelib/mera/metrics/power_metrics.py
mera-1.6.0.post1.data/purelib/mera/model/__init__.py
mera-1.6.0.post1.data/purelib/mera/model/input_desc.py
mera-1.6.0.post1.data/purelib/mera/pcie_driver/Makefile
mera-1.6.0.post1.data/purelib/mera/pcie_driver/pcieioctl.h
mera-1.6.0.post1.data/purelib/mera/pcie_driver/usd_pcie.c
mera-1.6.0.post1.data/purelib/mera/pcie_driver/usd_pcie.h
mera-1.6.0.post1.dist-info/LICENSE
mera-1.6.0.post1.dist-info/METADATA
mera-1.6.0.post1.dist-info/WHEEL
mera-1.6.0.post1.dist-info/entry_points.txt
mera-1.6.0.post1.dist-info/top_level.txt
mera-1.6.0.post1.dist-info/RECORD
