Metadata-Version: 2.1
Name: mera
Version: 1.6.0.post1
Summary: An heterogeneous deep learning compiler framework.
Home-page: https://github.com/Edgecortix-Inc/mera
Author: EdgeCortix Inc.
Author-email: mera-compiler@edgecortix.com
License: UNKNOWN
Project-URL: Bug Tracker, https://github.com/Edgecortix-Inc/mera/issues
Project-URL: Web Page, https://www.edgecortix.com
Platform: UNKNOWN
Classifier: Programming Language :: Python :: 3.6
Classifier: Programming Language :: Python :: 3.8
Classifier: License :: OSI Approved :: Apache Software License
Classifier: Operating System :: OS Independent
Classifier: Intended Audience :: Science/Research
Classifier: Topic :: Scientific/Engineering :: Artificial Intelligence
Classifier: Topic :: Software Development :: Compilers
Requires-Python: >=3.6
License-File: LICENSE
Requires-Dist: PyYAML
Requires-Dist: matplotlib
Requires-Dist: pytest
Requires-Dist: seaborn
Requires-Dist: tqdm
Provides-Extra: full
Requires-Dist: mera-tvm-full ; extra == 'full'
Requires-Dist: onednn-cpu-gomp (==2022.0.2) ; extra == 'full'
Requires-Dist: tensorflow (<=2.9.0) ; extra == 'full'
Requires-Dist: tflite (==2.4.0) ; extra == 'full'
Requires-Dist: torch (<=1.12.1) ; extra == 'full'
Requires-Dist: torchvision (<=0.13.1) ; extra == 'full'
Provides-Extra: runtime
Requires-Dist: mera-tvm-runtime ; extra == 'runtime'
